LICENSE
MANIFEST.in
README.rst
requirements.txt
setup.py
jeb/__init__.py
jeb/cli.py
jeb.egg-info/PKG-INFO
jeb.egg-info/SOURCES.txt
jeb.egg-info/dependency_links.txt
jeb.egg-info/entry_points.txt
jeb.egg-info/not-zip-safe
jeb.egg-info/requires.txt
jeb.egg-info/top_level.txt