Metadata-Version: 1.0
Name: jeb
Version: 1.1.1
Summary: JEB: Just Enough Blog
Home-page: https://github.com/ampledata/jeb
Author: Greg Albrecht
Author-email: gba@gregalbrecht.com
License: THE WORK (AS DEFINED BELOW) IS PROVIDED UNDER THE TERMS OF THIS CREATIVE COMMONS PUBLIC LICENSE ("CCPL" OR "LICENSE"). THE WORK IS PROTECTED BY COPYRIGHT AND/OR OTHER APPLICABLE LAW. ANY USE OF THE WORK OTHER THAN AS AUTHORIZED UNDER THIS LICENSE OR COPYRIGHT LAW IS PROHIBITED.
